Scarlet_Utils/__init__.py
Scarlet_Utils/__version__.py
Scarlet_Utils/chat.py
Scarlet_Utils/cog.py
Scarlet_Utils/cogsutils.py
Scarlet_Utils/consts.py
Scarlet_Utils/context.py
Scarlet_Utils/loop.py
Scarlet_Utils/menus.py
Scarlet_Utils/meta.py
Scarlet_Utils/sentry.py
Scarlet_Utils/settings.py
Scarlet_Utils/shared_cog.py
Scarlet_Utils/sqldriver.py
Scarlet_Utils/views.py
scarlet_utils-1.4.dist-info/licenses/LICENCE
scarlet_utils-1.4.dist-info/METADATA
scarlet_utils-1.4.dist-info/WHEEL
scarlet_utils-1.4.dist-info/top_level.txt
scarlet_utils-1.4.dist-info/RECORD
