Metadata-Version: 2.4
Name: Scarlet_Utils
Version: 1.4
Summary: Utils for StarBot.
Home-page: https://github.com/deathamongstlife/Star-Discord-Utils
Author: Scarlet Jean
Author-email: r79767525@gmail.com
Classifier: Programming Language :: Python :: 3
Classifier: Operating System :: OS Independent
Requires-Python: >=3.9.1
License-File: LICENCE
Requires-Dist: sentry_sdk
Requires-Dist: colorama
Dynamic: author
Dynamic: author-email
Dynamic: classifier
Dynamic: description
Dynamic: description-content-type
Dynamic: home-page
Dynamic: license-file
Dynamic: requires-dist
Dynamic: requires-python
Dynamic: summary
